domd/__init__.py
domd/api.py
domd/adapters/__init__.py
domd/adapters/api/__init__.py
domd/adapters/api/command_testing.py
domd/adapters/api/flask_api.py
domd/adapters/cli/__init__.py
domd/adapters/cli/command_presenter.py
domd/adapters/formatters/__init__.py
domd/adapters/formatters/markdown_formatter.py
domd/adapters/persistence/__init__.py
domd/adapters/persistence/in_memory_command_repository.py
domd/adapters/persistence/shell_command_executor.py
domd/application/__init__.py
domd/application/factory.py
domd/cli/__init__.py
domd/cli/cli.py
domd/command_execution/__init__.py
domd/core/__init__.py
domd/core/detector.py
domd/core/command_detection/__init__.py
domd/core/command_detection/base_detector.py
domd/core/command_detection/docker_tester.py
domd/core/command_detection/models.py
domd/core/command_detection/project_detector.py
domd/core/command_detection/handlers/__init__.py
domd/core/command_detection/handlers/command_handler.py
domd/core/command_detection/handlers/config_handler.py
domd/core/command_detection/parsers/__init__.py
domd/core/command_detection/parsers/base_parser.py
domd/core/command_detection/parsers/parser_registry.py
domd/core/command_detection/utils/__init__.py
domd/core/command_detection/utils/file_utils.py
domd/core/command_detection/utils/virtualenv.py
domd/core/command_execution/__init__.py
domd/core/command_execution/command_executor.py
domd/core/command_execution/command_recorder.py
domd/core/command_execution/command_runner.py
domd/core/command_execution/environment_detector.py
domd/core/command_execution/executor.py
domd/core/commands/__init__.py
domd/core/commands/command.py
domd/core/commands/executor.py
domd/core/domain/__init__.py
domd/core/domain/command.py
domd/core/parsers/__init__.py
domd/core/parsers/ansible_galaxy.py
domd/core/parsers/ansible_inventory.py
domd/core/parsers/ansible_playbook.py
domd/core/parsers/ansible_role.py
domd/core/parsers/ansible_vault.py
domd/core/parsers/base.py
domd/core/parsers/cargo_toml.py
domd-2.2.64.dist-info/licenses/LICENSE
domd-2.2.64.dist-info/METADATA
domd-2.2.64.dist-info/WHEEL
domd-2.2.64.dist-info/entry_points.txt
domd-2.2.64.dist-info/top_level.txt
domd-2.2.64.dist-info/RECORD
