Metadata-Version: 2.4
Name: domd
Version: 2.2.64
Summary: DoMD - Do Markdown Docs - automatically detect, run and show working commands in DONE.md and errors in TODO.md markdown files
Home-page: https://github.com/wronai/domd
Author: Tom Sapletta
Author-email: info@softreck.dev
License: Apache-2.0
Classifier: Development Status :: 3 - Alpha
Classifier: Intended Audience :: Developers
Classifier: Topic :: Software Development :: Quality Assurance
Classifier: Topic :: Software Development :: Build Tools
Classifier: Topic :: Software Development :: Testing
Classifier: Topic :: System :: Systems Administration
Classifier: License :: OSI Approved :: Apache Software License
Classifier: Programming Language :: Python :: 3
Classifier: Programming Language :: Python :: 3.9
Classifier: Programming Language :: Python :: 3.10
Classifier: Programming Language :: Python :: 3.11
Classifier: Programming Language :: Python :: 3.12
Classifier: Operating System :: OS Independent
Classifier: Environment :: Console
Classifier: Natural Language :: English
Requires-Python: >=3.9,<4.0
License-File: LICENSE
Requires-Dist: pyyaml>=6.0
Requires-Dist: toml>=0.10.2
Requires-Dist: configparser>=5.3.0
Requires-Dist: docker>=6.1.3
Requires-Dist: flask-cors>=6.0.1
Provides-Extra: dev
Requires-Dist: pytest>=7.0.0; extra == "dev"
Requires-Dist: pytest-cov>=4.0.0; extra == "dev"
Requires-Dist: pytest-mock>=3.10.0; extra == "dev"
Requires-Dist: pytest-docker>=2.0.0; extra == "dev"
Requires-Dist: black>=23.0.0; extra == "dev"
Requires-Dist: isort>=5.12.0; extra == "dev"
Requires-Dist: flake8>=6.0.0; extra == "dev"
Requires-Dist: mypy>=1.0.0; extra == "dev"
Requires-Dist: pylint>=2.17.0; extra == "dev"
Requires-Dist: pre-commit>=3.0.0; extra == "dev"
Requires-Dist: coverage[toml]>=7.0.0; extra == "dev"
Requires-Dist: codecov>=2.1.0; extra == "dev"
Dynamic: license-file
Dynamic: provides-extra
Dynamic: requires-dist
Dynamic: requires-python
